optimusprimal/Empty.py
optimusprimal/__init__.py
optimusprimal/grad_operators.py
optimusprimal/linear_operators.py
optimusprimal/map_uncertainty.py
optimusprimal/primal_dual.py
optimusprimal/prox_operators.py
optimusprimal-0.0.2.dist-info/LICENSE
optimusprimal-0.0.2.dist-info/METADATA
optimusprimal-0.0.2.dist-info/WHEEL
optimusprimal-0.0.2.dist-info/top_level.txt
optimusprimal-0.0.2.dist-info/RECORD
