Metadata-Version: 2.1
Name: optimusprimal
Version: 0.0.2
Summary: Convex Optimization Primal Dual Solver
Home-page: https://github.com/astro-informatics/Optimus-Primal
Author: Luke Pratley & Matthijs Mars & Matthew Price & Contributors
Author-email: luke.pratley@gmail.com
License: GNU General Public License v3 (GPLv3)
Platform: UNKNOWN
Classifier: Programming Language :: Python :: 3.6
Classifier: Programming Language :: Python :: 3.7
Classifier: Programming Language :: Python :: 3.8
Classifier: Operating System :: OS Independent
Classifier: Intended Audience :: Developers
Classifier: Intended Audience :: Science/Research
License-File: LICENSE
Requires-Dist: numpy
Requires-Dist: scipy
Requires-Dist: PyWavelets
Requires-Dist: black
